md_contents_table/__init__.py
md_contents_table/tests/md_contents_table_recursion.py
md_contents_table-1.0.0.dist-info/LICENSE
md_contents_table-1.0.0.dist-info/METADATA
md_contents_table-1.0.0.dist-info/WHEEL
md_contents_table-1.0.0.dist-info/top_level.txt
md_contents_table-1.0.0.dist-info/RECORD
