Metadata-Version: 2.1
Name: md_contents_table
Version: 1.0.0
Summary: This module can be used to create a contents table in a markdown file.
Author-email: DevDolphin7 <devdolphin7@outlook.com>
Project-URL: Homepage, https://github.com/DevDolphin7/mdContentsTable
Classifier: Programming Language :: Python :: 3
Classifier: License :: OSI Approved :: GNU General Public License v3 (GPLv3)
Classifier: Operating System :: OS Independent
Requires-Python: >=3.8
License-File: LICENSE
Provides-Extra: dev
Requires-Dist: pytest ; extra == 'dev'
Requires-Dist: pytest-describe ; extra == 'dev'
